[
  {
    "id": 1,
    "dni": "67890999",
    "nombre": "Roberta",
    "apellido": "Fernández",
    "mail": "roberta.fernandez@example.com",
    "contrasenia": "$2b$10$whatKSjghqD9uecmrtpfjOiJwvIN9IaAgaH0yOLmn/j4Rda8DdTMe",
    "celular": "1167894321",
    "rol_id": 1
  },
  {
    "id": 2,
    "dni": "67890123",
    "nombre": "Laura",
    "apellido": "Gómez",
    "mail": "laura.gomez@example.com",
    "contrasenia": "$2b$10$whatKSjghqD9uecmrtpfjOiJwvIN9IaAgaH0yOLmn/j4Rda8DdTMe",
    "celular": "1167894322",
    "rol_id": "3"
  },
  {
    "id": 3,
    "dni": "67890124",
    "nombre": "Fernanda",
    "apellido": "Martínez",
    "mail": "fernanda.martinez@example.com",
    "contrasenia": "$2b$10$whatKSjghqD9uecmrtpfjOiJwvIN9IaAgaH0yOLmn/j4Rda8DdTMe",
    "celular": "1167894323",
    "rol_id": "2"
  },
  {
    "id": 4,
    "dni": "67890124",
    "nombre": "Daniela",
    "apellido": "Suárez",
    "mail": "daniela.suarez@example.com",
    "contrasenia": "$2b$10$whatKSjghqD9uecmrtpfjOiJwvIN9IaAgaH0yOLmn/j4Rda8DdTMe",
    "celular": "1167894323",
    "rol_id": "2"
  },
  {
    "id": 5,
    "dni": "67890111",
    "nombre": "Gloria",
    "apellido": "Ramírez",
    "mail": "gloria.ramirez@example.com",
    "contrasenia": "$2b$10$whatKSjghqD9uecmrtpfjOiJwvIN9IaAgaH0yOLmn/j4Rda8DdTMe",
    "celular": "1160001001",
    "rol_id": 1
  },
  {
    "id": 6,
    "dni": "67890112",
    "nombre": "Mariano",
    "apellido": "Pérez",
    "mail": "mariano.perez@example.com",
    "contrasenia": "$2b$10$whatKSjghqD9uecmrtpfjOiJwvIN9IaAgaH0yOLmn/j4Rda8DdTMe",
    "celular": "1160001002",
    "rol_id": 1
  },
  {
    "id": 7,
    "dni": "67890113",
    "nombre": "Nicolás",
    "apellido": "Sánchez",
    "mail": "nicolas.sanchez@example.com",
    "contrasenia": "$2b$10$whatKSjghqD9uecmrtpfjOiJwvIN9IaAgaH0yOLmn/j4Rda8DdTMe",
    "celular": "1160001003",
    "rol_id": 1
  },
  {
    "id": 8,
    "dni": "67890114",
    "nombre": "Lucas",
    "apellido": "Moreno",
    "mail": "lucas.moreno@example.com",
    "contrasenia": "$2b$10$whatKSjghqD9uecmrtpfjOiJwvIN9IaAgaH0yOLmn/j4Rda8DdTMe",
    "celular": "1160001004",
    "rol_id": 1
  },
  {
    "id": 9,
    "dni": "67890115",
    "nombre": "Emilia",
    "apellido": "Torres",
    "mail": "emilia.torres@example.com",
    "contrasenia": "$2b$10$whatKSjghqD9uecmrtpfjOiJwvIN9IaAgaH0yOLmn/j4Rda8DdTMe",
    "celular": "1160001005",
    "rol_id": 1
  },
  {
    "id": 10,
    "dni": "67890116",
    "nombre": "Bruno",
    "apellido": "Sivori",
    "mail": "bruno.sivori@example.com",
    "contrasenia": "$2b$10$whatKSjghqD9uecmrtpfjOiJwvIN9IaAgaH0yOLmn/j4Rda8DdTMe",
    "celular": "1160001006",
    "rol_id": 1
  },
  {
    "id": 11,
    "dni": "67890117",
    "nombre": "Milena",
    "apellido": "García",
    "mail": "milena.garcia@example.com",
    "contrasenia": "$2b$10$whatKSjghqD9uecmrtpfjOiJwvIN9IaAgaH0yOLmn/j4Rda8DdTMe",
    "celular": "1160001007",
    "rol_id": 1
  },
  {
    "id": 12,
    "dni": "67890118",
    "nombre": "Augusto",
    "apellido": "Vega",
    "mail": "augusto.vega@example.com",
    "contrasenia": "$2b$10$whatKSjghqD9uecmrtpfjOiJwvIN9IaAgaH0yOLmn/j4Rda8DdTMe",
    "celular": "1160001008",
    "rol_id": 1
  },
  {
    "id": 13,
    "dni": "67890119",
    "nombre": "Camilo",
    "apellido": "López",
    "mail": "camilo.lopez@example.com",
    "contrasenia": "$2b$10$whatKSjghqD9uecmrtpfjOiJwvIN9IaAgaH0yOLmn/j4Rda8DdTMe",
    "celular": "1160001009",
    "rol_id": 1
  },
  {
    "id": 14,
    "dni": "67890120",
    "nombre": "Mariana",
    "apellido": "Ortega",
    "mail": "mariana.ortega@example.com",
    "contrasenia": "$2b$10$whatKSjghqD9uecmrtpfjOiJwvIN9IaAgaH0yOLmn/j4Rda8DdTMe",
    "celular": "1160001010",
    "rol_id": 1
  },
  {
    "id": 15,
    "dni": "67890121",
    "nombre": "Bianca",
    "apellido": "Ruiz",
    "mail": "bianca.ruiz@example.com",
    "contrasenia": "$2b$10$whatKSjghqD9uecmrtpfjOiJwvIN9IaAgaH0yOLmn/j4Rda8DdTMe",
    "celular": "1160001011",
    "rol_id": 1
  },
  {
    "id": 16,
    "dni": "67890122",
    "nombre": "Matías",
    "apellido": "Castro",
    "mail": "matias.castro@example.com",
    "contrasenia": "$2b$10$whatKSjghqD9uecmrtpfjOiJwvIN9IaAgaH0yOLmn/j4Rda8DdTMe",
    "celular": "1160001012",
    "rol_id": 1
  },
  {
    "id": 17,
    "dni": "67890123",
    "nombre": "Morena",
    "apellido": "Silva",
    "mail": "morena.silva@example.com",
    "contrasenia": "$2b$10$whatKSjghqD9uecmrtpfjOiJwvIN9IaAgaH0yOLmn/j4Rda8DdTMe",
    "celular": "1160001013",
    "rol_id": 1
  },
  {
    "id": 18,
    "dni": "67890124",
    "nombre": "Sebastián",
    "apellido": "Domínguez",
    "mail": "sebastian.dominguez@example.com",
    "contrasenia": "$2b$10$whatKSjghqD9uecmrtpfjOiJwvIN9IaAgaH0yOLmn/j4Rda8DdTMe",
    "celular": "1160001014",
    "rol_id": 1
  },
  {
    "id": 19,
    "dni": "67890125",
    "nombre": "Violeta",
    "apellido": "Molina",
    "mail": "violeta.molina@example.com",
    "contrasenia": "$2b$10$whatKSjghqD9uecmrtpfjOiJwvIN9IaAgaH0yOLmn/j4Rda8DdTMe",
    "celular": "1160001015",
    "rol_id": 1
  }
]
